validate_pyproject/__init__.py
validate_pyproject/__main__.py
validate_pyproject/_tomllib.py
validate_pyproject/api.py
validate_pyproject/caching.py
validate_pyproject/cli.py
validate_pyproject/error_reporting.py
validate_pyproject/errors.py
validate_pyproject/extra_validations.py
validate_pyproject/formats.py
validate_pyproject/http.py
validate_pyproject/project_metadata.schema.json
validate_pyproject/py.typed
validate_pyproject/pyproject_toml.schema.json
validate_pyproject/remote.py
validate_pyproject/repo_review.py
validate_pyproject/types.py
validate_pyproject/plugins/__init__.py
validate_pyproject/plugins/distutils.schema.json
validate_pyproject/plugins/setuptools.schema.json
validate_pyproject/pre_compile/NOTICE.template
validate_pyproject/pre_compile/__init__.py
validate_pyproject/pre_compile/__main__.py
validate_pyproject/pre_compile/api-notice.template
validate_pyproject/pre_compile/cli-notice.template
validate_pyproject/pre_compile/cli.py
validate_pyproject/pre_compile/main_file.template
validate_pyproject/vendoring/__init__.py
validate_pyproject/vendoring/__main__.py
validate_pyproject/vendoring/cli.py
validate_pyproject-0.24.1.dist-info/AUTHORS.rst
validate_pyproject-0.24.1.dist-info/LICENSE.txt
validate_pyproject-0.24.1.dist-info/METADATA
validate_pyproject-0.24.1.dist-info/NOTICE.txt
validate_pyproject-0.24.1.dist-info/WHEEL
validate_pyproject-0.24.1.dist-info/entry_points.txt
validate_pyproject-0.24.1.dist-info/top_level.txt
validate_pyproject-0.24.1.dist-info/RECORD
