Metadata-Version: 2.1
Name: validate-pyproject
Version: 0.24.1
Summary: Validation library and CLI tool for checking on 'pyproject.toml' files using JSON Schema
Author-email: Anderson Bravalheri <andersonbravalheri@gmail.com>
License: MPL-2.0 and MIT and BSD-3-Clause
Project-URL: Homepage, https://github.com/abravalheri/validate-pyproject/
Project-URL: Documentation, https://validate-pyproject.readthedocs.io/
Project-URL: Source, https://github.com/abravalheri/validate-pyproject
Project-URL: Tracker, https://github.com/abravalheri/validate-pyproject/issues
Project-URL: Changelog, https://validate-pyproject.readthedocs.io/en/latest/changelog.html
Project-URL: Download, https://pypi.org/project/validate-pyproject/#files
Classifier: Development Status :: 4 - Beta
Classifier: Intended Audience :: Developers
Classifier: Operating System :: OS Independent
Classifier: Programming Language :: Python
Classifier: Topic :: Software Development :: Quality Assurance
Classifier: Typing :: Typed
Requires-Python: >=3.8
License-File: LICENSE.txt
License-File: NOTICE.txt
License-File: AUTHORS.rst
Requires-Dist: fastjsonschema<=3,>=2.16.2
Provides-Extra: all
Requires-Dist: packaging>=24.2; extra == "all"
Requires-Dist: tomli>=1.2.1; python_version < "3.11" and extra == "all"
Requires-Dist: trove-classifiers>=2021.10.20; extra == "all"
Provides-Extra: store
Requires-Dist: validate-pyproject-schema-store; extra == "store"
